rasterinlay/__init__.py
rasterinlay/_doc.py
rasterinlay/_static_version.py
rasterinlay/_version.py
rasterinlay/blocks.py
rasterinlay/distribute.py
rasterinlay/helpers.py
rasterinlay/raredist.py
RasterInLay-0.1.2rc0.dist-info/METADATA
RasterInLay-0.1.2rc0.dist-info/WHEEL
RasterInLay-0.1.2rc0.dist-info/top_level.txt
RasterInLay-0.1.2rc0.dist-info/RECORD
